md_to_jira/__init__.py
md_to_jira/jira_to_md.py
md_to_jira/md_to_jira.py
md_to_jira-1.0.4.dist-info/METADATA
md_to_jira-1.0.4.dist-info/WHEEL
md_to_jira-1.0.4.dist-info/entry_points.txt
md_to_jira-1.0.4.dist-info/licenses/LICENSE
md_to_jira-1.0.4.dist-info/RECORD
