Metadata-Version: 2.4
Name: md-to-jira
Version: 1.0.4
Summary: Simple Python utilities for converting from GitHub-flavored Markdown syntax to Atlassian's custom markup syntax, and vice-versa
Project-URL: Homepage, https://github.com/eshack94/md-to-jira
Project-URL: Repository, https://github.com/eshack94/md-to-jira
Project-URL: Issues, https://github.com/eshack94/md-to-jira/issues
Author-email: Elijah Shackelford <eshack94@users.noreply.github.com>
License: MIT License
License-File: LICENSE
Keywords: atlassian,confluence,converter,jira,markdown,markup
Classifier: Development Status :: 4 - Beta
Classifier: Intended Audience :: Developers
Classifier: License :: OSI Approved :: MIT License
Classifier: Operating System :: OS Independent
Classifier: Programming Language :: Python :: 3
Classifier: Programming Language :: Python :: 3.6
Classifier: Programming Language :: Python :: 3.7
Classifier: Programming Language :: Python :: 3.8
Classifier: Programming Language :: Python :: 3.9
Classifier: Programming Language :: Python :: 3.10
Classifier: Programming Language :: Python :: 3.11
Classifier: Programming Language :: Python :: 3.12
Classifier: Topic :: Software Development :: Libraries :: Python Modules
Classifier: Topic :: Text Processing :: Markup
Requires-Python: >=3.6
